py2neo_compat/__init__.py
py2neo_compat/py2neo_compat.py
py2neo_compat/schema.py
py2neo_compat/util.py
py2neo_compat-1.0.1.dist-info/METADATA
py2neo_compat-1.0.1.dist-info/RECORD
py2neo_compat-1.0.1.dist-info/WHEEL
py2neo_compat-1.0.1.dist-info/top_level.txt
