Metadata-Version: 2.1
Name: py2neo_compat
Version: 1.0.1
Summary: Compatibility layer for py2neo
Home-page: https://github.com/wcooley/py2neo_compat
Author: Wil Cooley
Author-email: wcooley@nakedape.cc
License: Apache Software License 2.0
Keywords: py2neo_compat py2neo compat neo4j
Platform: UNKNOWN
Classifier: Development Status :: 2 - Pre-Alpha
Classifier: Intended Audience :: Developers
Classifier: License :: OSI Approved :: Apache Software License
Classifier: Natural Language :: English
Classifier: Programming Language :: Python :: 2
Classifier: Programming Language :: Python :: 2.7
Classifier: Programming Language :: Python :: 3
Classifier: Programming Language :: Python :: 3.4
Classifier: Programming Language :: Python :: 3.5
Classifier: Programming Language :: Python :: 3.6
Provides-Extra: test
